README.md
setup.py
openmensa/__init__.py
openmensa_api.egg-info/PKG-INFO
openmensa_api.egg-info/SOURCES.txt
openmensa_api.egg-info/dependency_links.txt
openmensa_api.egg-info/top_level.txt