Metadata-Version: 1.1
Name: openmensa-api
Version: 1.1
Summary: Library to talk to OpenMensa API v2
Home-page: https://github.com/brennerm/openmensa-api
Author: Max Brenner
Author-email: xamrennerb@gmail.com
License: UNKNOWN
Download-URL: https://github.com/brennerm/openmensa-api/archive/1.1.tar.gz
Keywords: openmensa,api
Platform: UNKNOWN
